[
  {
    "id": 1,
    "movie_id": 1,
    "room_id": 1,
    "date": "10/02/2023",
    "time": ["14:00", "16:00", "18:00"]
  },
  {
    "id": 2,
    "movie_id": 2,
    "room_id": 2,
    "date": "10/02/2023",
    "time": ["15:00", "17:00", "19:00"]
  },
  {
    "id": 3,
    "movie_id": 3,
    "room_id": 1,
    "date": "11/02/2023",
    "time": ["14:00", "16:00", "18:00"]
  },
  {
    "id": 4,
    "movie_id": 4,
    "room_id": 2,
    "date": "11/02/2023",
    "time": ["15:00", "17:00", "19:00"]
  },
  {
    "id": 5,
    "movie_id": 5,
    "room_id": 1,
    "date": "12/02/2023",
    "time": ["14:00", "16:00", "18:00"]
  },
  {
    "id": 6,
    "movie_id": 6,
    "room_id": 2,
    "date": "12/02/2023",
    "time": ["15:00", "17:00", "19:00"]
  },
  {
    "id": 7,
    "movie_id": 1,
    "room_id": 1,
    "date": "13/02/2023",
    "time": ["14:00", "16:00", "18:00"]
  },
  {
    "id": 8,
    "movie_id": 2,
    "room_id": 2,
    "date": "13/02/2023",
    "time": ["15:00", "17:00", "19:00"]
  },
  {
    "id": 9,
    "movie_id": 3,
    "room_id": 1,
    "date": "14/02/2023",
    "time": ["14:00", "16:00", "18:00"]
  },
  {
    "id": 10,
    "movie_id": 4,
    "room_id": 2,
    "date": "14/02/2023",
    "time": ["15:00", "17:00", "19:00"]
  },
  {
    "id": 11,
    "movie_id": 5,
    "room_id": 1,
    "date": "15/02/2023",
    "time": ["14:00", "16:00", "18:00"]
  },
  {
    "id": 12,
    "movie_id": 1,
    "room_id": 1,
    "date": "15/02/2023",
    "time": ["14:00", "17:00", "20:00"]
  },
  {
    "id": 13,
    "movie_id": 2,
    "room_id": 2,
    "date": "16/02/2023",
    "time": ["14:30", "18:00", "20:30"]
  },
  {
    "id": 14,
    "movie_id": 3,
    "room_id": 1,
    "date": "16/02/2023",
    "time": ["15:00", "17:30", "21:00"]
  },
  {
    "id": 15,
    "movie_id": 4,
    "room_id": 2,
    "date": "17/02/2023",
    "time": ["15:30", "18:30", "21:30"]
  },
  {
    "id": 16,
    "movie_id": 1,
    "room_id": 2,
    "date": "17/02/2023",
    "time": ["14:00", "17:00", "20:00"]
  },
  {
    "id": 17,
    "movie_id": 2,
    "room_id": 1,
    "date": "18/02/2023",
    "time": ["14:30", "18:00", "20:30"]
  },
  {
    "id": 18,
    "movie_id": 3,
    "room_id": 2,
    "date": "18/02/2023",
    "time": ["15:00", "17:30", "21:00"]
  },
  {
    "id": 19,
    "movie_id": 4,
    "room_id": 1,
    "date": "19/02/2023",
    "time": ["15:30", "18:30", "21:30"]
  },
  {
    "id": 20,
    "movie_id": 5,
    "room_id": 2,
    "date": "19/02/2023",
    "time": ["16:00", "19:00", "22:00"]
  },{
  "id": 21,
  "movie_id": 1,
  "room_id": 1,
  "date": "20/02/2023",
  "time": ["14:00", "17:00", "20:00"]
},
  {
    "id": 22,
    "movie_id": 2,
    "room_id": 2,
    "date": "20/02/2023",
    "time": ["14:30", "18:00", "20:30"]
  },
  {
    "id": 23,
    "movie_id": 3,
    "room_id": 1,
    "date": "20/02/2023",
    "time": ["15:00", "17:30", "21:00"]
  },
  {
    "id": 24,
    "movie_id": 4,
    "room_id": 2,
    "date": "20/02/2023",
    "time": ["15:30", "18:30", "21:30"]
  },
  {
    "id": 25,
    "movie_id": 5,
    "room_id": 1,
    "date": "20/02/2023",
    "time": ["16:00", "19:00", "22:00"]
  },
  {
    "id": 26,
    "movie_id": 6,
    "room_id": 2,
    "date": "20/02/2023",
    "time": ["16:30", "19:30", "22:30"]
  },
  {
    "id": 27,
    "movie_id": 1,
    "room_id": 1,
    "date": "21/02/2023",
    "time": ["14:00", "17:00", "20:00"]
  },
  {
    "id": 28,
    "movie_id": 2,
    "room_id": 2,
    "date": "21/02/2023",
    "time": ["14:30", "18:00", "20:30"]
  },
  {
    "id": 29,
    "movie_id": 3,
    "room_id": 1,
    "date": "21/02/2023",
    "time": ["15:00", "17:30", "21:00"]
  },
  {
    "id": 30,
    "movie_id": 4,
    "room_id": 2,
    "date": "21/02/2023",
    "time": ["15:30", "18:30", "21:30"]
  }
]